proxyplucker/__init__.py
proxyplucker/freeproxylistnet/__init__.py
proxyplucker-0.0.2.dist-info/LICENSE
proxyplucker-0.0.2.dist-info/METADATA
proxyplucker-0.0.2.dist-info/WHEEL
proxyplucker-0.0.2.dist-info/top_level.txt
proxyplucker-0.0.2.dist-info/RECORD
