Metadata-Version: 2.1
Name: proxyplucker
Version: 0.0.2
Summary: Get List Of Online Proxy Servers In Json
Home-page: UNKNOWN
Author: Shivjeet Singh Bhullar
Author-email: bhullarshivjeet@gmail.com
License: UNKNOWN
Platform: UNKNOWN
Classifier: Programming Language :: Python :: 3
Classifier: License :: OSI Approved :: GNU General Public License v3 or later (GPLv3+)
Classifier: Operating System :: OS Independent
Requires-Python: >=3.1
Requires-Dist: webplucker (==0.0.3)
